odoo/addons/purchase_work_acceptance_evaluation/README.rst
odoo/addons/purchase_work_acceptance_evaluation/__init__.py
odoo/addons/purchase_work_acceptance_evaluation/__manifest__.py
odoo/addons/purchase_work_acceptance_evaluation/demo/evaluation_data.xml
odoo/addons/purchase_work_acceptance_evaluation/i18n/pt_BR.po
odoo/addons/purchase_work_acceptance_evaluation/i18n/purchase_work_acceptance_evaluation.pot
odoo/addons/purchase_work_acceptance_evaluation/models/__init__.py
odoo/addons/purchase_work_acceptance_evaluation/models/res_config_settings.py
odoo/addons/purchase_work_acceptance_evaluation/models/work_acceptance.py
odoo/addons/purchase_work_acceptance_evaluation/models/work_acceptance_evaluation.py
odoo/addons/purchase_work_acceptance_evaluation/readme/CONFIGURE.rst
odoo/addons/purchase_work_acceptance_evaluation/readme/CONTRIBUTORS.rst
odoo/addons/purchase_work_acceptance_evaluation/readme/DESCRIPTION.rst
odoo/addons/purchase_work_acceptance_evaluation/readme/USAGE.rst
odoo/addons/purchase_work_acceptance_evaluation/report/__init__.py
odoo/addons/purchase_work_acceptance_evaluation/report/work_acceptance_evaluation_report.py
odoo/addons/purchase_work_acceptance_evaluation/report/work_acceptance_evaluation_report.xml
odoo/addons/purchase_work_acceptance_evaluation/security/ir.model.access.csv
odoo/addons/purchase_work_acceptance_evaluation/security/security.xml
odoo/addons/purchase_work_acceptance_evaluation/static/description/icon.png
odoo/addons/purchase_work_acceptance_evaluation/static/description/index.html
odoo/addons/purchase_work_acceptance_evaluation/tests/__init__.py
odoo/addons/purchase_work_acceptance_evaluation/tests/test_purchase_work_acceptance_evaluation.py
odoo/addons/purchase_work_acceptance_evaluation/views/res_config_settings_views.xml
odoo/addons/purchase_work_acceptance_evaluation/views/work_acceptance_evaluation_views.xml
odoo/addons/purchase_work_acceptance_evaluation/views/work_acceptance_views.xml
odoo14_addon_purchase_work_acceptance_evaluation-14.0.2.0.1.dist-info/METADATA
odoo14_addon_purchase_work_acceptance_evaluation-14.0.2.0.1.dist-info/WHEEL
odoo14_addon_purchase_work_acceptance_evaluation-14.0.2.0.1.dist-info/top_level.txt
odoo14_addon_purchase_work_acceptance_evaluation-14.0.2.0.1.dist-info/RECORD
